MANIFEST.in
README.txt
setup.py
docs/COPYRIGHT.txt
docs/CREDITS.txt
docs/HISTORY.txt
docs/LICENSE.txt
src/dolmen/__init__.py
src/dolmen.sqlcontainer.egg-info/PKG-INFO
src/dolmen.sqlcontainer.egg-info/SOURCES.txt
src/dolmen.sqlcontainer.egg-info/dependency_links.txt
src/dolmen.sqlcontainer.egg-info/entry_points.txt
src/dolmen.sqlcontainer.egg-info/namespace_packages.txt
src/dolmen.sqlcontainer.egg-info/not-zip-safe
src/dolmen.sqlcontainer.egg-info/requires.txt
src/dolmen.sqlcontainer.egg-info/top_level.txt
src/dolmen/sqlcontainer/__init__.py
src/dolmen/sqlcontainer/components.py
src/dolmen/sqlcontainer/interfaces.py
src/dolmen/sqlcontainer/test_container.py