Metadata-Version: 1.1
Name: dolmen.sqlcontainer
Version: 0.3
Summary: Container abstraction for SQLAlchemy
Home-page: http://gitweb.dolmen-project.org
Author: The Dolmen team
Author-email: dolmen@list.dolmen-project.org
License: ZPL 2.1
Keywords: Dolmen Container SQLAlchemy
Platform: UNKNOWN
Classifier: Environment :: Web Environment
Classifier: License :: OSI Approved :: Zope Public License
Classifier: Programming Language :: Python
